smart_data/__init__.py
smart_data/_version.py
smart_data/include.py
tests/__init__.py
tests/test_include.py
smart_data-0.2.0.dist-info/LICENSE
smart_data-0.2.0.dist-info/METADATA
smart_data-0.2.0.dist-info/WHEEL
smart_data-0.2.0.dist-info/top_level.txt
smart_data-0.2.0.dist-info/RECORD
