Metadata-Version: 2.1
Name: smart-data
Version: 0.2.0
Summary: Smart comparing data for tests
Home-page: https://github.com/pkoscielny/smart_data
Author: Pawel Koscielny
License: UNKNOWN
Project-URL: Bug Tracker, https://github.com/pkoscielny/smart_data/issues
Platform: UNKNOWN
Classifier: Programming Language :: Python
Classifier: Programming Language :: Python :: 3
Classifier: License :: OSI Approved :: MIT License
Classifier: Operating System :: OS Independent
Classifier: Topic :: Software Development :: Libraries :: Python Modules
Requires-Python: >=3.6.9
